[
    {
        "id": 1779648421237,
        "name": "01",
        "price": 17,
        "images": [
            "images\/file_6a1347a35163d4.91671838.png",
            "images\/file_6a1347a35185b5.15078990.png",
            "images\/file_6a1347a351a474.98009073.png",
            "images\/file_6a1347a351c3b2.07648118.png",
            "images\/file_6a1347a351e1c3.54737818.png",
            "images\/file_6a1347a35201b8.10171672.png"
        ],
        "video": "videos\/file_6a1347a3521fe3.57420801.mp4",
        "description": "Бутилка едно човече.Червена капачка \/ Кавал \/ маса Наздраве.\nРазмери на Бутилката.\nД - 80мм\nШ - 60мм\nВ - 270мм\n",
        "tags": [
            "Бутилки",
            "Податръци",
            "Сувенири"
        ],
        "category": "Бутилки 1 човече",
        "available": true
    },
    {
        "id": 1779648728661,
        "name": "05",
        "price": 22,
        "images": [
            "images\/file_6a1348d6de2bb4.51304180.png",
            "images\/file_6a1348d6de4f96.67752771.png",
            "images\/file_6a1348d6de6f93.13904766.png",
            "images\/file_6a1348d6de8fe3.78561866.png",
            "images\/file_6a1348d6deaed9.09998283.png"
        ],
        "video": "videos\/file_6a1348d6dece51.68330966.mp4",
        "description": "Бутилка 2 човечета.Зелена капачка Кавал + Гайда\nМаса Наздраве\nРазмери:\nД - 85мм\nШ - 60мм\nВ - 260мм",
        "tags": [
            "Бутилки",
            "Податръци",
            "Сувенири"
        ],
        "category": "Бутилки 2 човечета",
        "available": true
    },
    {
        "id": 1779719021343,
        "name": "12",
        "price": 26,
        "images": [
            "images\/file_6a145b6c193070.83203403.png",
            "images\/file_6a145b6c1965b9.84684986.png",
            "images\/file_6a145b6c1986c9.51771025.png",
            "images\/file_6a145b6c19a6d2.07888491.png",
            "images\/file_6a145b6c19cb46.11134722.png",
            "images\/file_6a145b6c19eb17.04851058.png",
            "images\/file_6a145b6c1a0ad4.36100364.png"
        ],
        "video": "videos\/file_6a145b6c1a2d26.19898660.mp4",
        "description": "Бутилка с три човечета. Маса Шевица\nРазмери:\nД -85мм\nШ -70мм\nВ -295мм",
        "tags": [
            "Бутилки",
            "Податръци",
            "Сувенири"
        ],
        "category": "Бутилки 3 човечета",
        "available": true
    },
    {
        "id": 1779719310567,
        "name": "02",
        "price": 16,
        "images": [
            "images\/file_6a145c8d0f5747.45586250.png",
            "images\/file_6a145c8d0f7a31.87714338.png",
            "images\/file_6a145c8d0f99e9.34664604.png",
            "images\/file_6a145c8d0fba91.10376966.png",
            "images\/file_6a145c8d0fda41.73892118.png",
            "images\/file_6a145c8d0ff988.50247018.png"
        ],
        "video": "videos\/file_6a145c8d1023f9.89782063.mp4",
        "description": "Бутилка 1 човече с Кавал. Маса Наздраве добре дошли.\nРазмери:\nФ - 70мм\nВ - 295мм",
        "tags": [
            "Бутилки",
            "Податръци",
            "Сувенири"
        ],
        "category": "Бутилки 1 човече",
        "available": true
    },
    {
        "id": 1779719468871,
        "name": "03",
        "price": 16,
        "images": [
            "images\/file_6a145d2bce5095.97639571.png",
            "images\/file_6a145d2bce7383.03273080.png",
            "images\/file_6a145d2bce9588.28960117.png",
            "images\/file_6a145d2bcebaf9.49969214.png",
            "images\/file_6a145d2bcedb10.70416550.png"
        ],
        "video": "videos\/file_6a145d2bcefc08.30332899.mp4",
        "description": "Бутилка 1 човече с кавал.Маса Нездраве добре дошли.\nРазмери:\nФ - 70мм\nВ - 295мм",
        "tags": [
            "Бутилки",
            "Податръци",
            "Сувенири"
        ],
        "category": "Бутилки 1 човече",
        "available": true
    },
    {
        "id": 1779719617167,
        "name": "04",
        "price": 17,
        "images": [
            "images\/file_6a145dbf5048e8.99233999.png",
            "images\/file_6a145dbf506c08.97971702.png",
            "images\/file_6a145dbf508c95.74403568.png",
            "images\/file_6a145dbf50ad42.63790357.png",
            "images\/file_6a145dbf50cda3.98073434.png"
        ],
        "video": "videos\/file_6a145dbf50ed55.49011715.mp4",
        "description": "Бутилка 1 човече с Кавал.Червена капачка.\nМаса Наздраве добре дощли\nРазмери:\nД -80мм\nШ -60мм\nВ -270мм",
        "tags": [
            "Бутилки",
            "Податръци",
            "Сувенири"
        ],
        "category": "Бутилки 1 човече",
        "available": true
    },
    {
        "id": 1779719826423,
        "name": "06",
        "price": 22,
        "images": [
            "images\/file_6a145e9162f042.83065342.png",
            "images\/file_6a145e916313b0.38486105.png",
            "images\/file_6a145e91633428.59986531.png",
            "images\/file_6a145e91635411.97980701.png",
            "images\/file_6a145e91638d83.98827142.png",
            "images\/file_6a145e9163aef6.26550572.png"
        ],
        "video": "videos\/file_6a145e9163cf88.96263168.mp4",
        "description": "Бутилка 2 човечета\/Гайда + Гъдулка\nМаса -  Наздраве\nРазмери;\nД -100мм\nШ -60мм\nВ -290мм",
        "tags": [
            "Бутилки",
            "Податръци",
            "Сувенири"
        ],
        "category": "Бутилки 2 човечета",
        "available": true
    },
    {
        "id": 1779720077294,
        "name": "07",
        "price": 30,
        "images": [
            "images\/file_6a145f8ba7f156.78137910.png",
            "images\/file_6a145f8ba81768.29728836.png",
            "images\/file_6a145f8ba838e0.34627400.png",
            "images\/file_6a145f8ba85aa7.59828937.png",
            "images\/file_6a145f8ba87ab4.92580105.png",
            "images\/file_6a145f8ba89db0.14158406.png"
        ],
        "video": "videos\/file_6a145f8ba8bdd8.26387626.mp4",
        "description": "Бутилка 1л. Парашутист .Синя капачка.\nМного ефектна бутилка . Трудна за изработка.\nРазмери:\nД -70мм\nШ -70мм\nВ -320мм",
        "tags": [
            "Бутилки",
            "Податръци",
            "Сувенири"
        ],
        "category": "Бутилки 1 човече",
        "available": true
    },
    {
        "id": 1779720637774,
        "name": "08",
        "price": 30,
        "images": [
            "images\/file_6a1461a8cdc900.66388131.png",
            "images\/file_6a1461a8cded55.71497393.png",
            "images\/file_6a1461a8ce1365.70802691.png",
            "images\/file_6a1461a8ce3500.13966045.png",
            "images\/file_6a1461a8ce5589.47242894.png"
        ],
        "video": "videos\/file_6a1461a8ce7639.50068056.mp4",
        "description": "Бутилка 1л Наклонен Парашутист.Синя капачка.\nБутилката е много ефектна.            \nМного трудна за изработка за това цената е такава.\nРазмери:\nД -70мм\nш -70мм\nВ -320мм\n",
        "tags": [
            "Бутилки",
            "Податръци",
            "Сувенири"
        ],
        "category": "Бутилки 1 човече",
        "available": true
    },
    {
        "id": 1779720804302,
        "name": "09",
        "price": 31,
        "images": [
            "images\/file_6a146262d58760.73016861.png",
            "images\/file_6a146262d5b027.84184013.png",
            "images\/file_6a146262d5d202.30964522.png",
            "images\/file_6a146262d5f1c1.98150909.png",
            "images\/file_6a146262d611d2.05932984.png"
        ],
        "video": "videos\/file_6a146262d63528.16761619.mp4",
        "description": "Бутилка 1л Парашутист с автомат.\nМного ефектна бутилка.Трудна за изработка.\nРазмери:\nД -70мм\nШ -70мм\nВ -320мм",
        "tags": [
            "Бутилки",
            "Податръци",
            "Сувенири"
        ],
        "category": "Бутилки 1 човече",
        "available": true
    },
    {
        "id": 1779721384574,
        "name": "10",
        "price": 30,
        "images": [
            "images\/file_6a1464a651f123.74680409.png",
            "images\/file_6a1464a6521bc1.08648184.png",
            "images\/file_6a1464a6523cc7.56591434.png",
            "images\/file_6a1464a6525fe9.91254659.png",
            "images\/file_6a1464a6527ff3.13683362.png",
            "images\/file_6a1464a652a080.22383004.png"
        ],
        "video": "videos\/file_6a1464a652c1b6.23523257.mp4",
        "description": "Бутилка 1л парашутист.Черна капачка\nМного ефектна бутилка.\nРазмери:\nД -70мм\nШ -70мм\nВ -320мм",
        "tags": [
            "Бутилки",
            "Податръци",
            "Сувенири"
        ],
        "category": "Бутилки 1 човече",
        "available": true
    },
    {
        "id": 1779721542917,
        "name": "11",
        "price": 31,
        "images": [
            "images\/file_6a14654512d335.69499441.png",
            "images\/file_6a14654512f734.16492133.png",
            "images\/file_6a146545131822.18647221.png",
            "images\/file_6a14654513a4c6.25707871.png",
            "images\/file_6a14654513cda4.45752579.png"
        ],
        "video": "videos\/file_6a14654513ee92.07014106.mp4",
        "description": "Бутилка 1л Парашутист с Автомат.\nМного ефектна бутилка. Трудна за изработка.\nКлипът е на моя лична бутилка.\nРазмери:\nД -70мм\nШ -70мм\nВ -320мм",
        "tags": [
            "Бутилки",
            "Податръци",
            "Сувенири"
        ],
        "category": "Бутилки 1 човече",
        "available": true
    },
    {
        "id": 1779721727621,
        "name": "13",
        "price": 26,
        "images": [
            "images\/file_6a1465fe02edf6.76806128.png",
            "images\/file_6a1465fe0311f1.88281908.png",
            "images\/file_6a1465fe033305.75263417.png",
            "images\/file_6a1465fe0354f6.03936950.png",
            "images\/file_6a1465fe0375b2.51282410.png",
            "images\/file_6a1465fe039705.99172864.png"
        ],
        "video": "videos\/file_6a1465fe03b727.89241799.mp4",
        "description": "Бутилка 1л Три човечета.\nМаса \/ Наздраве добре дошли\nРазмери:\nД -85мм\nШ -70мм\nВ -295мм",
        "tags": [
            "Бутилки",
            "Податръци",
            "Сувенири"
        ],
        "category": "Бутилки 3 човечета",
        "available": true
    },
    {
        "id": 1779721851597,
        "name": "14",
        "price": 26,
        "images": [
            "images\/file_6a14667a7f2155.19450377.png",
            "images\/file_6a14667a7f4723.85084033.png",
            "images\/file_6a14667a7f6816.43816789.png",
            "images\/file_6a14667a7f8870.53787068.png",
            "images\/file_6a14667a7fab21.25630942.png",
            "images\/file_6a14667a7fcbf4.96990822.png"
        ],
        "video": "videos\/file_6a14667a7fed26.04814236.mp4",
        "description": "Бутилка 1л Три човечета.\nМаса  \/Добре дошли наздраве\nРазмери:\nД -85мм\nШ -70мм\nВ -295мм",
        "tags": [
            "Бутилки",
            "Податръци",
            "Сувенири"
        ],
        "category": "Бутилки 3 човечета",
        "available": true
    },
    {
        "id": 1779721985445,
        "name": "15",
        "price": 26,
        "images": [
            "images\/file_6a1467001edbd6.77858382.png",
            "images\/file_6a1467001f05d5.38903430.png",
            "images\/file_6a1467001f26e2.13550733.png",
            "images\/file_6a1467001f47d4.25942558.png",
            "images\/file_6a1467001f6c78.47523681.png",
            "images\/file_6a1467001f9093.37670862.png"
        ],
        "video": "videos\/file_6a1467001fb109.71201219.mp4",
        "description": "Бутилка 1л Три човечета.\nМаса \/ Наздраве\nРазмери:\nД -85мм\nШ -70мм\nВ -295мм\n",
        "tags": [
            "Бутилки",
            "Податръци",
            "Сувенири"
        ],
        "category": "Бутилки 3 човечета",
        "available": true
    },
    {
        "id": 1779722139101,
        "name": "16",
        "price": 26,
        "images": [
            "images\/file_6a146799bfcfb2.53612709.png",
            "images\/file_6a146799bff394.08806071.png",
            "images\/file_6a146799c014b7.41100247.png",
            "images\/file_6a146799c03597.48831645.png",
            "images\/file_6a146799c05654.11803667.png",
            "images\/file_6a146799c076f1.81626727.png"
        ],
        "video": "videos\/file_6a146799c09767.15053597.mp4",
        "description": "Бутилка 1л Три човечета.\nМаса \/Наздраве добре дошли\nРазмери:\nД -85мм\nШ -70мм\nВ -295мм",
        "tags": [
            "Бутилки",
            "Податръци",
            "Сувенири"
        ],
        "category": "Бутилки 3 човечета",
        "available": true
    },
    {
        "id": 1779722376021,
        "name": "17",
        "price": 26,
        "images": [
            "images\/file_6a146887348df5.62759834.png",
            "images\/file_6a14688734b2a0.18020928.png",
            "images\/file_6a14688734d341.13104729.png",
            "images\/file_6a14688734f3f1.40597963.png",
            "images\/file_6a1468873513d3.62590000.png",
            "images\/file_6a146887353462.74236827.png"
        ],
        "video": "videos\/file_6a146887355756.80559619.mp4",
        "description": "Бутилка 1л Три човечета.\nМаса \/Добре дошли наздраве.\nРазмери:\nД -85мм\nШ -70мм\nВ -295мм",
        "tags": [
            "Бутилки",
            "Податръци",
            "Сувенири"
        ],
        "category": "Бутилки 3 човечета",
        "available": true
    },
    {
        "id": 1779722515485,
        "name": "18",
        "price": 26,
        "images": [
            "images\/file_6a146912088dc9.98985206.png",
            "images\/file_6a14691208b209.80090841.png",
            "images\/file_6a14691208d3b9.05873954.png",
            "images\/file_6a14691208f490.43448734.png",
            "images\/file_6a146912091557.19138475.png",
            "images\/file_6a146912093562.40004820.png"
        ],
        "video": "videos\/file_6a146912095556.51647717.mp4",
        "description": "Бутилка 1л Три човечета.\nМаса \/Наздраве добре дошли.\nРазмери:\nД -85мм\nШ -70мм\nВ -295мм\n",
        "tags": [
            "Бутилки",
            "Податръци",
            "Сувенири"
        ],
        "category": "Бутилки 3 човечета",
        "available": true
    },
    {
        "id": 1779722762180,
        "name": "19",
        "price": 26,
        "images": [
            "images\/file_6a146a087fbd71.09114519.png",
            "images\/file_6a146a087fe3f2.42122808.png",
            "images\/file_6a146a088005a5.97930519.png",
            "images\/file_6a146a08802716.11740625.png",
            "images\/file_6a146a08804874.07604277.png",
            "images\/file_6a146a08807405.76967533.png"
        ],
        "video": "videos\/file_6a146a08809705.20482522.mp4",
        "description": "Бутилка 1л Три човечета.\nНарочно съм запазил етикета понеже неизглежда добре.\nМаса \/Добре дошли наздраве\nРазмери:\nД -80мм\nШ -70мм\nВ -300мм",
        "tags": [
            "Бутилки",
            "Податръци",
            "Сувенири"
        ],
        "category": "Бутилки 3 човечета",
        "available": true
    },
    {
        "id": 1779722935836,
        "name": "20",
        "price": 25,
        "images": [
            "images\/file_6a146ab65d8704.02345849.png",
            "images\/file_6a146ab65dab79.60289304.png",
            "images\/file_6a146ab65dccb5.71270981.png",
            "images\/file_6a146ab65ded71.45946910.png",
            "images\/file_6a146ab65e0da7.08733482.png",
            "images\/file_6a146ab65e2ed5.85481679.png"
        ],
        "video": "videos\/file_6a146ab65e4f15.23106823.mp4",
        "description": "Бутилка 0,700 Три човечета\nМаса \/ Шевица\nРазмери:\nД -80мм\nШ -70мм\nВ -270мм",
        "tags": [
            "Бутилки",
            "Податръци",
            "Сувенири"
        ],
        "category": "Бутилки 3 човечета",
        "available": true
    },
    {
        "id": 1779723064756,
        "name": "21",
        "price": 26,
        "images": [
            "images\/file_6a146b35a3ec38.19669912.png",
            "images\/file_6a146b35a414b7.02622012.png",
            "images\/file_6a146b35a435d3.06143709.png",
            "images\/file_6a146b35a45946.55577511.png",
            "images\/file_6a146b35a47a10.22360255.png",
            "images\/file_6a146b35a49b24.50506195.png"
        ],
        "video": "videos\/file_6a146b35a4bb35.01674861.mp4",
        "description": "Бутилка 1л Три човечета.\nМаса \/Добре дошли наздраве.\nРазмери:\nД -85мм\nШ -70мм\nВ -295мм",
        "tags": [
            "Бутилки",
            "Податръци",
            "Сувенири"
        ],
        "category": "Бутилки 3 човечета",
        "available": true
    },
    {
        "id": 1779723354668,
        "name": "22",
        "price": 26,
        "images": [
            "images\/file_6a146c596e37a8.10899506.png",
            "images\/file_6a146c596e5ee6.88657335.png",
            "images\/file_6a146c596e8a00.34040950.png",
            "images\/file_6a146c596eaf39.48304773.png",
            "images\/file_6a146c596f05a7.61898340.png",
            "images\/file_6a146c596f7b26.65690196.png"
        ],
        "video": "videos\/file_6a146c596faca9.62818968.mp4",
        "description": "Бутилка 1л Три човечета.\nЕтикета е запазен умишлено.Може да се премахне ако желаете.\nБез етикет не изглежда добре според мен.\nМаса \/Наздраве добре дошли\nРазмери:\nД -80мм\nШ -70мм\nВ -300мм",
        "tags": [
            "Бутилки",
            "Податръци",
            "Сувенири"
        ],
        "category": "Бутилки 3 човечета",
        "available": true
    },
    {
        "id": 1779723586300,
        "name": "23",
        "price": 27,
        "images": [
            "images\/file_6a146d40bc2fc7.70285661.png",
            "images\/file_6a146d40bc53e3.28215053.png",
            "images\/file_6a146d40bc76a9.97674791.png",
            "images\/file_6a146d40bc9f69.45033657.png",
            "images\/file_6a146d40bcc3e3.75345027.png",
            "images\/file_6a146d40bce469.31135757.png"
        ],
        "video": "videos\/file_6a146d40bd04c1.18045102.mp4",
        "description": "Бутилка 1л Три човечета.\nМаса \/ Наздраве добре дошли.\nРазмери:\nД -85мм\nШ -85мм\nВ -285мм",
        "tags": [
            "Бутилки",
            "Податръци",
            "Сувенири",
            "Подарък за рожден ден",
            "Подарък за имен ден."
        ],
        "category": "Бутилки 3 човечета",
        "available": true
    },
    {
        "id": 1779723717236,
        "name": "24",
        "price": 25,
        "images": [
            "images\/file_6a146dc373a3f9.47094260.png",
            "images\/file_6a146dc373c7d4.61428336.png",
            "images\/file_6a146dc373e8b2.87479105.png",
            "images\/file_6a146dc3740909.63267277.png",
            "images\/file_6a146dc3742af8.49053273.png",
            "images\/file_6a146dc3744d21.02676126.png"
        ],
        "video": "videos\/file_6a146dc3746df5.16414087.mp4",
        "description": "Бутилка 0,700мл. Три човечета.\nМаса \/ Наздраве\nРазмери:\nД -75мм\nШ -75мм\nВ -260мм",
        "tags": [
            "Бутилки",
            "Податръци",
            "Сувенири",
            "Подарък за рожден ден",
            "Подарък за имен ден."
        ],
        "category": "Бутилки 3 човечета",
        "available": true
    },
    {
        "id": 1779723925532,
        "name": "25",
        "price": 27,
        "images": [
            "images\/file_6a146e942c12c1.44047233.png",
            "images\/file_6a146e942c37b8.29898743.png",
            "images\/file_6a146e942c5938.06624377.png",
            "images\/file_6a146e942c7a10.26879631.png",
            "images\/file_6a146e942c9af7.13397021.png",
            "images\/file_6a146e942cbbe9.21555470.png"
        ],
        "video": "videos\/file_6a146e942cdc39.62628835.mp4",
        "description": "Бутилка 1л. Три човечета.\nМаса \/Наздраве добре дошли\nРазмери:\nД -85мм\nШ -85мм\nВ -285мм",
        "tags": [
            "Бутилки",
            "Податръци",
            "Сувенири",
            "Подарък за рожден ден",
            "Подарък за имен ден."
        ],
        "category": "Бутилки 3 човечета",
        "available": true
    },
    {
        "id": 1779724070571,
        "name": "26",
        "price": 25,
        "images": [
            "images\/file_6a146f2554de21.72630514.png",
            "images\/file_6a146f255501a2.67398295.png",
            "images\/file_6a146f255522f6.76594205.png",
            "images\/file_6a146f25554337.76560325.png",
            "images\/file_6a146f25556341.32355175.png",
            "images\/file_6a146f25558353.58570745.png"
        ],
        "video": "videos\/file_6a146f2555a323.46774543.mp4",
        "description": "Бутилка 0,700мл.Три човечета.\nМаса \/Добре дошли наздраве.\nРазмери:\nД -75мм\nШ -75мм\nВ -260мм\n",
        "tags": [
            "Бутилки",
            "Податръци",
            "Сувенири",
            "Подарък за рожден ден",
            "Подарък за имен ден."
        ],
        "category": "Бутилки 3 човечета",
        "available": true
    },
    {
        "id": 1779724249059,
        "name": "27",
        "price": 22,
        "images": [
            "images\/file_6a146fd7cc77e6.53718872.png",
            "images\/file_6a146fd7cc9c92.92648758.png",
            "images\/file_6a146fd7ccbe56.18404410.png",
            "images\/file_6a146fd7ccdef7.94405485.png",
            "images\/file_6a146fd7ccff97.65766296.png"
        ],
        "video": "videos\/file_6a146fd7cd2022.90502946.mp4",
        "description": "Бутилка 1Л. Едно човече с Кавал.\nМаса \/Наздраве + Ваза с цветя.\nРазмери:\nД -100мм\nШ -70мм\nВ -305мм",
        "tags": [
            "Бутилки",
            "Податръци",
            "Сувенири",
            "Подарък за рожден ден",
            "Подарък за имен ден."
        ],
        "category": "Бутилки 1 човече",
        "available": true
    },
    {
        "id": 1779724461907,
        "name": "28",
        "price": 23,
        "images": [
            "images\/file_6a1470ab075280.20223065.png",
            "images\/file_6a1470ab077753.03324323.png",
            "images\/file_6a1470ab079981.29372100.png",
            "images\/file_6a1470ab07b9a8.26377437.png",
            "images\/file_6a1470ab07da06.11668396.png",
            "images\/file_6a1470ab07fa75.08141114.png"
        ],
        "video": "videos\/file_6a1470ab082143.65803206.mp4",
        "description": "Бутилка 1Л. Сърце с криле.\nПодходяща за Семеен подарък за новородено или Кръщене.\nРазмери:\nД -85мм\nШ -85мм\nВ -270мм",
        "tags": [
            "Бутилки",
            "Податръци",
            "Сувенири",
            "Подарък за рожден ден",
            "Подарък за имен ден."
        ],
        "category": "Бутилки 1 човече",
        "available": true
    },
    {
        "id": 1779724613987,
        "name": "29",
        "price": 26,
        "images": [
            "images\/file_6a147143e9d892.19758711.png",
            "images\/file_6a147143e9fce3.67876784.png",
            "images\/file_6a147143ea1f66.80180937.png",
            "images\/file_6a147143ea4166.19122370.png",
            "images\/file_6a147143ea61f0.46729798.png",
            "images\/file_6a147143ea8440.27564719.png"
        ],
        "video": "videos\/file_6a147143eaa6b4.72543636.mp4",
        "description": "Бутилка 1Л.Три човечета.\nМаса \/ шевица + Наздраве\nРазмери:\nД -85мм\nШ -70мм\nВ -295мм",
        "tags": [
            "Бутилки",
            "Податръци",
            "Сувенири",
            "Подарък за рожден ден",
            "Подарък за имен ден."
        ],
        "category": "Бутилки 3 човечета",
        "available": true
    },
    {
        "id": 1779724754755,
        "name": "30",
        "price": 26,
        "images": [
            "images\/file_6a1471ca718800.71794114.png",
            "images\/file_6a1471ca71abe3.12935893.png",
            "images\/file_6a1471ca71ce03.49068577.png",
            "images\/file_6a1471ca71ee79.86188930.png",
            "images\/file_6a1471ca720f74.59880870.png",
            "images\/file_6a1471ca722ff4.72636469.png"
        ],
        "video": "videos\/file_6a1471ca725232.69268799.mp4",
        "description": "Бутилка 0,700мл.Три човечета.\nМаса \/Шевица\nРазмери:\nД -75мм\nШ -75мм\nВ -245мм",
        "tags": [
            "Бутилки",
            "Податръци",
            "Сувенири",
            "Подарък за рожден ден",
            "Подарък за имен ден."
        ],
        "category": "Бутилки 3 човечета",
        "available": true
    },
    {
        "id": 1779724878563,
        "name": "31",
        "price": 28,
        "images": [
            "images\/file_6a14724d2237e3.42392546.png",
            "images\/file_6a14724d225cd2.95359796.png",
            "images\/file_6a14724d228090.64247920.png",
            "images\/file_6a14724d22a139.15061343.png",
            "images\/file_6a14724d22c1b9.82380352.png",
            "images\/file_6a14724d22e206.80221322.png"
        ],
        "video": "videos\/file_6a14724d230288.62421902.mp4",
        "description": "Бутилка 1л.Три човечета.\nМаса \/ Наздраве добре дошли.\nРазмери:\nд -85мм\nШ -85мм\nВ -270мм",
        "tags": [
            "Бутилки",
            "Податръци",
            "Сувенири",
            "Подарък за рожден ден",
            "Подарък за имен ден."
        ],
        "category": "Бутилки 3 човечета",
        "available": true
    },
    {
        "id": 1779725042115,
        "name": "32",
        "price": 27,
        "images": [
            "images\/file_6a1472f09b2d29.10901340.png",
            "images\/file_6a1472f09b5734.33041026.png",
            "images\/file_6a1472f09b7af4.91623898.png",
            "images\/file_6a1472f09ba377.26158075.png",
            "images\/file_6a1472f09bc964.32497442.png",
            "images\/file_6a1472f09bef30.07947668.png"
        ],
        "video": "videos\/file_6a1472f09c14f8.57696845.mp4",
        "description": "Бутилка 1л.Три човечета.\nМаса \/ Наздраве добре дошли + Ваза с цветя.\nРазмери:\nД -85мм\nШ -85мм\nВ -290мм\n",
        "tags": [
            "Бутилки",
            "Податръци",
            "Сувенири",
            "Подарък за рожден ден",
            "Подарък за имен ден."
        ],
        "category": "Бутилки 3 човечета",
        "available": true
    },
    {
        "id": 1779725162459,
        "name": "33",
        "price": 26,
        "images": [
            "images\/file_6a147369227754.36888241.png",
            "images\/file_6a147369229bb5.88743136.png",
            "images\/file_6a14736922bcc2.72449564.png",
            "images\/file_6a14736922de03.96135429.png",
            "images\/file_6a14736922fee4.01329944.png",
            "images\/file_6a147369232082.92728412.png"
        ],
        "video": "videos\/file_6a147369234158.88039940.mp4",
        "description": "Бутилка 0,700мл.Три човечета.\nМаса \/Наздраве добре дошли.\nРазмери:\nД -75мм\nШ -75мм\nВ -245мм",
        "tags": [
            "Бутилки",
            "Податръци",
            "Сувенири",
            "Подарък за рожден ден",
            "Подарък за имен ден."
        ],
        "category": "Бутилки 3 човечета",
        "available": true
    },
    {
        "id": 1779725289315,
        "name": "34",
        "price": 28,
        "images": [
            "images\/file_6a1473e849b1e2.80397949.png",
            "images\/file_6a1473e849d735.16849760.png",
            "images\/file_6a1473e849f861.75078313.png",
            "images\/file_6a1473e84a18b9.18829545.png",
            "images\/file_6a1473e84a38d5.50773108.png",
            "images\/file_6a1473e84a5901.80047635.png"
        ],
        "video": "videos\/file_6a1473e84a7968.01323506.mp4",
        "description": "Бутилка 1л.Три човечета.\nМаса \/Добре дошли наздраве\nРазмери:\nД -85мм\nШ -85мм\nВ -270мм",
        "tags": [
            "Бутилки",
            "Податръци",
            "Сувенири",
            "Подарък за рожден ден",
            "Подарък за имен ден."
        ],
        "category": "Бутилки 3 човечета",
        "available": true
    },
    {
        "id": 1779725592891,
        "name": "35",
        "price": 28,
        "images": [
            "images\/file_6a147517869244.89086039.png",
            "images\/file_6a14751786b6a8.07567932.png",
            "images\/file_6a14751786d878.34756310.png",
            "images\/file_6a14751786f980.64625502.png",
            "images\/file_6a147517871b35.48156074.png",
            "images\/file_6a147517873bf8.97775294.png"
        ],
        "video": "videos\/file_6a147517875ca2.84538320.mp4",
        "description": "Бутилка 1л.Три човечета.\nМаса \/Наздраве добре дошли.\nРазмери:\nД -85мм\nШ -85мм\nВ -270мм",
        "tags": [
            "Бутилки",
            "Податръци",
            "Сувенири",
            "Подарък за рожден ден",
            "Подарък за имен ден."
        ],
        "category": "Бутилки 3 човечета",
        "available": true
    },
    {
        "id": 1779725798618,
        "name": "36",
        "price": 26,
        "images": [
            "images\/file_6a1475e533a308.97201736.png",
            "images\/file_6a1475e533c940.19231294.png",
            "images\/file_6a1475e533ea79.36255296.png",
            "images\/file_6a1475e5340d22.03275896.png",
            "images\/file_6a1475e5342f11.62088531.png",
            "images\/file_6a1475e5345019.95251653.png"
        ],
        "video": "videos\/file_6a1475e53470a9.96878356.mp4",
        "description": "Бутилка 0,700мл.Три човечета. Кръгла.\nМаса \/Наздраве добре дошли.\nРазмери:\nФ -80мм\nВ -240мм\n",
        "tags": [
            "Бутилки",
            "Податръци",
            "Сувенири",
            "Подарък за рожден ден",
            "Подарък за имен ден."
        ],
        "category": "Бутилки 3 човечета",
        "available": true
    },
    {
        "id": 1779725984922,
        "name": "37",
        "price": 25,
        "images": [
            "images\/file_6a1476a016e215.30131113.png",
            "images\/file_6a1476a0170832.48229727.png",
            "images\/file_6a1476a0172a48.70539306.png",
            "images\/file_6a1476a0174b90.17206003.png",
            "images\/file_6a1476a0177858.95165504.png",
            "images\/file_6a1476a0179c26.86190236.png"
        ],
        "video": "videos\/file_6a1476a017be97.28184317.mp4",
        "description": "Бутилка 0,700мл.Три човечета.\nМаса \/ Шевица\nРазмери:\nД -75мм\nШ -75мм\nВ -265мм",
        "tags": [
            "Бутилки",
            "Податръци",
            "Сувенири",
            "Подарък за рожден ден",
            "Подарък за имен ден."
        ],
        "category": "Бутилки 3 човечета",
        "available": true
    },
    {
        "id": 1779726208170,
        "name": "38",
        "price": 28,
        "images": [
            "images\/file_6a14777e36aec6.84707970.png",
            "images\/file_6a14777e36d394.33233549.png",
            "images\/file_6a14777e36f5d2.17869192.png",
            "images\/file_6a14777e3716a4.57542953.png",
            "images\/file_6a14777e373751.98854090.png",
            "images\/file_6a14777e375818.38871456.png"
        ],
        "video": "videos\/file_6a14777e377913.50930407.mp4",
        "description": "Бутилка 1л.Три човечета.\nМаса \/Welcome Cheers - Добре дошли наздраве.\nРазмери:\nД -85мм\nШ -85мм\nВ -270мм",
        "tags": [
            "Бутилки",
            "Податръци",
            "Сувенири",
            "Подарък за рожден ден",
            "Подарък за имен ден."
        ],
        "category": "Бутилки 3 човечета",
        "available": true
    },
    {
        "id": 1779726415762,
        "name": "39",
        "price": 28,
        "images": [
            "images\/file_6a14784e011420.43453981.png",
            "images\/file_6a14784e013990.54861829.png",
            "images\/file_6a14784e015b99.97697007.png",
            "images\/file_6a14784e017e75.45773538.png",
            "images\/file_6a14784e01a0c2.19349013.png",
            "images\/file_6a14784e01c1c8.51582917.png"
        ],
        "video": "videos\/file_6a14784e01e378.44341393.mp4",
        "description": "Бутилка 1л.Три човечета.\nМаса \/Tradition in a Bottle - Традиция в Бутилка.\nРазмери:\nД -85мм\nШ -85мм\nВ -270мм",
        "tags": [
            "Бутилки",
            "Податръци",
            "Сувенири",
            "Подарък за рожден ден",
            "Подарък за имен ден."
        ],
        "category": "Бутилки 3 човечета",
        "available": true
    },
    {
        "id": 1779726599554,
        "name": "40",
        "price": 22,
        "images": [
            "images\/file_6a147906310aa1.00128965.png",
            "images\/file_6a147906313278.17551333.png",
            "images\/file_6a1479063155a2.27278170.png",
            "images\/file_6a147906317680.16860911.png",
            "images\/file_6a147906319731.85485926.png",
            "images\/file_6a14790631b7e6.23132779.png"
        ],
        "video": "videos\/file_6a14790631d887.78813603.mp4",
        "description": "Бутилка 1л.Две човечета.Кавал+ Гъдулка\nМаса \/Шевица\nРазмер:\nД -90мм\nШ -55мм\nВ -300мм",
        "tags": [
            "Бутилки",
            "Податръци",
            "Сувенири",
            "Подарък за рожден ден",
            "Подарък за имен ден."
        ],
        "category": "Бутилки 2 човечета",
        "available": true
    },
    {
        "id": 1779726819186,
        "name": "41",
        "price": 16,
        "images": [
            "images\/file_6a1479e189c1b2.75268931.png",
            "images\/file_6a1479e189e7d6.04722408.png",
            "images\/file_6a1479e18a08d6.35787181.png",
            "images\/file_6a1479e18a2986.26231053.png",
            "images\/file_6a1479e18a4a41.04033160.png"
        ],
        "video": "videos\/file_6a1479e18a6b80.81996383.mp4",
        "description": "Бутилка 0,700мл.Едно човече с Кавал.\nМаса \/Шевица   Бутилката е триъгълна.\nРазмери:\nД -80мм\nШ -75мм\nВ -295мм",
        "tags": [
            "Бутилки",
            "Податръци",
            "Сувенири",
            "Подарък за рожден ден",
            "Подарък за имен ден."
        ],
        "category": "Бутилки 1 човече",
        "available": true
    },
    {
        "id": 1779726927881,
        "name": "42",
        "price": 26,
        "images": [
            "images\/file_6a147a4eeebf06.94046404.png",
            "images\/file_6a147a4eeee721.07785216.png",
            "images\/file_6a147a4eef0937.53141083.png",
            "images\/file_6a147a4eef2ae7.35831561.png",
            "images\/file_6a147a4eef4b86.23583093.png",
            "images\/file_6a147a4eef6bc4.80264190.png"
        ],
        "video": "videos\/file_6a147a4eef8d51.30949069.mp4",
        "description": "Бутилка 1л.Три човечета.\nМаса \/Щевица\nРазмери:\nД -85мм\nШ -70мм\nВ -295мм",
        "tags": [
            "Бутилки",
            "Податръци",
            "Сувенири",
            "Подарък за рожден ден",
            "Подарък за имен ден."
        ],
        "category": "Бутилки 3 човечета",
        "available": true
    },
    {
        "id": 1779727377929,
        "name": "43",
        "price": 23,
        "images": [
            "images\/file_6a147c108e3967.09288926.png",
            "images\/file_6a147c108e5eb9.91529295.png",
            "images\/file_6a147c108e7fe6.71919444.png",
            "images\/file_6a147c108ea076.32737548.png",
            "images\/file_6a147c108ec1d6.62947048.png",
            "images\/file_6a147c108ee2c1.03279152.png"
        ],
        "video": "videos\/file_6a147c108f0337.06887445.mp4",
        "description": "Бутилка 1л.Трчи човечета.\nМаса \/ Наздраве.\nРазмер:\nД -75мм\nШ -75мм\nВ -320мм\n\n",
        "tags": [
            "Бутилки",
            "Податръци",
            "Сувенири",
            "Подарък за рожден ден",
            "Подарък за имен ден."
        ],
        "category": "Бутилки 3 човечета",
        "available": true
    },
    {
        "id": 1779727486553,
        "name": "44",
        "price": 17,
        "images": [
            "images\/file_6a147c7cbf3583.78119617.png",
            "images\/file_6a147c7cbf5b11.35439770.png",
            "images\/file_6a147c7cbf7ce4.30855125.png",
            "images\/file_6a147c7cbf9ec2.12259516.png",
            "images\/file_6a147c7cbfc028.72955079.png"
        ],
        "video": "videos\/file_6a147c7cbfe694.27754165.mp4",
        "description": "Бутилка 0,700мл.Едно човече с Гайда.\nМаса \/Наздраве\nРазмери:\nД -80мм\nШ -60мм\nВ -270мм",
        "tags": [
            "Бутилки",
            "Податръци",
            "Сувенири",
            "Подарък за рожден ден",
            "Подарък за имен ден."
        ],
        "category": "Бутилки 1 човече",
        "available": true
    },
    {
        "id": 1779727665305,
        "name": "45",
        "price": 16,
        "images": [
            "images\/file_6a147d2fe39192.92110876.png",
            "images\/file_6a147d2fe3b6a0.24771897.png",
            "images\/file_6a147d2fe3d7d3.77432353.png",
            "images\/file_6a147d2fe3f863.60851495.png",
            "images\/file_6a147d2fe418f3.77058189.png"
        ],
        "video": "videos\/file_6a147d2fe439a0.60527596.mp4",
        "description": "Бутилка 0,500мл.Едно човече с Кавал.\nМаса \/Шевица\nРазмери:\nД -65мм\nШ -60мм\nВ -250мм",
        "tags": [
            "Бутилки",
            "Податръци",
            "Сувенири",
            "Подарък за рожден ден",
            "Подарък за имен ден."
        ],
        "category": "Бутилки 1 човече",
        "available": true
    },
    {
        "id": 1779727783929,
        "name": "46",
        "price": 24,
        "images": [
            "images\/file_6a147da6b7ad13.74925067.png",
            "images\/file_6a147da6b7d2f2.80028865.png",
            "images\/file_6a147da6b7f4b9.06526750.png",
            "images\/file_6a147da6b815b1.89110097.png",
            "images\/file_6a147da6b836c6.84032916.png",
            "images\/file_6a147da6b85751.97493914.png"
        ],
        "video": "videos\/file_6a147da6b877e7.15711348.mp4",
        "description": "Бутилка 0,700мл.Три човечета.\nМаса \/Наздраве добре дошли.\nРазмери:\nД -75мм\nШ -75мм\nВ -265мм",
        "tags": [
            "Бутилки",
            "Податръци",
            "Сувенири",
            "Подарък за рожден ден",
            "Подарък за имен ден."
        ],
        "category": "Бутилки 3 човечета",
        "available": true
    },
    {
        "id": 1779727889273,
        "name": "47",
        "price": 26,
        "images": [
            "images\/file_6a147e0f55c0e0.37131363.png",
            "images\/file_6a147e0f55ecd4.43159362.png",
            "images\/file_6a147e0f560e80.18122550.png",
            "images\/file_6a147e0f563055.79598647.png",
            "images\/file_6a147e0f5650f2.93605689.png",
            "images\/file_6a147e0f5670e8.93883065.png"
        ],
        "video": "videos\/file_6a147e0f5690f6.23610490.mp4",
        "description": "Бутилка 1л.Три човечета.\nМаса \/Наздраве добре дошли.\nРазмери:\nД -85мм\nШ -70мм\nВ -295мм\n",
        "tags": [
            "Бутилки",
            "Податръци",
            "Сувенири"
        ],
        "category": "Бутилки 3 човечета",
        "available": true
    },
    {
        "id": 1779728191593,
        "name": "48",
        "price": 26,
        "images": [
            "images\/file_6a147f3df1deb3.22119131.png",
            "images\/file_6a147f3df20345.08788413.png",
            "images\/file_6a147f3df22573.38363055.png",
            "images\/file_6a147f3df25797.04999694.png",
            "images\/file_6a147f3df27c40.83555058.png",
            "images\/file_6a147f3df29cb4.69230363.png"
        ],
        "video": "videos\/file_6a147f3df2bde1.06102125.mp4",
        "description": "Бутилка 1л.Три човечета.\nМаса \/ Красива Звезда.Етикета е запазен умишлено.Изглежда по добре но може да се махне при ваше желание.\nРазмери:\nД -80мм\nШ -70мм\nВ -300мм",
        "tags": [
            "Бутилки",
            "Податръци",
            "Сувенири",
            "Подарък за рожден ден",
            "Подарък за имен ден."
        ],
        "category": "Бутилки 3 човечета",
        "available": true
    },
    {
        "id": 1779728323408,
        "name": "49",
        "price": 25,
        "images": [
            "images\/file_6a147fc21dbf96.65550859.png",
            "images\/file_6a147fc21de4a0.67582985.png",
            "images\/file_6a147fc21e0982.71133501.png",
            "images\/file_6a147fc21e2aa9.88304935.png",
            "images\/file_6a147fc21e4c28.18460290.png",
            "images\/file_6a147fc21e6e48.99290465.png"
        ],
        "video": "videos\/file_6a147fc21e8e97.65322262.mp4",
        "description": "Бутилка 0,700мл.Три човечета.\nМаса \/Наздраве добре дошли.\nРазмер:\nД -75мм\nШ -75мм\nВ 260мм",
        "tags": [
            "Бутилки",
            "Податръци",
            "Сувенири"
        ],
        "category": "Бутилки 3 човечета",
        "available": true
    },
    {
        "id": 1779728435448,
        "name": "50",
        "price": 25,
        "images": [
            "images\/file_6a1480323ea592.87166449.png",
            "images\/file_6a1480323eca48.18549870.png",
            "images\/file_6a1480323eeba1.78504014.png",
            "images\/file_6a1480323f0c54.80741005.png",
            "images\/file_6a1480323f3214.28716741.png",
            "images\/file_6a1480323f5394.75838863.png"
        ],
        "video": "videos\/file_6a1480323f74b6.47315009.mp4",
        "description": "Бутилка 0,700мл.Три човечета.\nМаса \/Наздраве добре дошли.\nРазмер:\nД -75мм\nШ -75мм\nВ -260мм",
        "tags": [
            "Бутилки",
            "Податръци",
            "Сувенири",
            "Подарък за рожден ден",
            "Подарък за имен ден."
        ],
        "category": "Бутилки 3 човечета",
        "available": true
    },
    {
        "id": 1779728564488,
        "name": "51",
        "price": 16,
        "images": [
            "images\/file_6a1480b2645e82.42763609.png",
            "images\/file_6a1480b2648303.70227765.png",
            "images\/file_6a1480b264a4b9.28427692.png",
            "images\/file_6a1480b264c521.10367313.png",
            "images\/file_6a1480b264e5f9.09636968.png"
        ],
        "video": "videos\/file_6a1480b26507d8.60510133.mp4",
        "description": "Бутилка 0,700мл.Едно човече с Кавал.\nМаса \/Наздраве.\nРазмери:\nФ -70мм\nВ -300мм",
        "tags": [
            "Бутилки",
            "Податръци",
            "Сувенири"
        ],
        "category": "Бутилки 1 човече",
        "available": true
    },
    {
        "id": 1780083423957,
        "name": "Валентин",
        "price": 1000000,
        "images": [
            "images\/file_6a19eade9e37b5.32469048.jpg",
            "images\/file_6a19eade9f5fc0.66070064.jpg",
            "images\/file_6a19eade9fc6d9.60540451.jpg"
        ],
        "video": "videos\/file_6a19eadea03297.77562944.mp4",
        "description": "избери ако ти харесва моят забавен магазин",
        "tags": [
            "Разни"
        ],
        "category": "За всекиго по нещо",
        "available": true
    },
    {
        "id": 1780083979805,
        "name": "Аз",
        "price": 0.01,
        "images": [
            "images\/file_6a19ed0adca0f9.96148775.jpg"
        ],
        "video": "videos\/file_6a19ed0adcc506.62690976.mp4",
        "description": "аз съм бе .все тъка евтин.",
        "tags": [
            "Разни"
        ],
        "category": "За всекиго по нещо",
        "available": true
    },
    {
        "id": 1780084084356,
        "name": "Аз",
        "price": 0.001,
        "images": [
            "images\/file_6a19ed7389d5a0.18247881.jpg"
        ],
        "video": "videos\/file_6a19ed7389fd85.14735253.mp4",
        "description": "пак съм аз",
        "tags": [
            "Разни"
        ],
        "category": "За всекиго по нещо",
        "available": true
    },
    {
        "id": 1780084296868,
        "name": "мой неща",
        "price": 1,
        "images": [
            "images\/file_6a19ee36517fb2.23276303.jpg"
        ],
        "video": null,
        "description": "мой",
        "tags": [],
        "category": "За всекиго по нещо",
        "available": true
    },
    {
        "id": 1780124122045,
        "name": "Кумовете",
        "price": 1000000,
        "images": [
            "images\/file_6a1a89d8b0d643.66622206.jpg"
        ],
        "video": null,
        "description": "Малък Спомен.НАЗДРАВЕ КУМЕ.",
        "tags": [
            ""
        ],
        "category": "За всекиго по нещо",
        "available": true
    }
]